Metadata-Version: 1.0
Name: merchant-wallet-libs
Version: 0.0.0
Summary: Foo
Home-page: https://squadrone@bitbucket.org/bar/foo.git
Author: Squadrone
Author-email: foo@bar.com
License: UNKNOWN
Platform: UNKNOWN
